{"cameraMode":{"drawMode":0,"name":"Shaded","section":"Shading Mode"},"sceneLighting":true,"audioPlay":false,"sceneViewState":{"m_AlwaysRefresh":false,"showFog":true,"showSkybox":true,"showFlares":true,"showImageEffects":true,"showParticleSystems":true,"showVisualEffectGraphs":true,"m_FxEnabled":true},"in2DMode":false,"pivot":{"x":1.5978360176086426,"y":-2.483599901199341,"z":0.1099977120757103},"rotation":{"x":0.48209747672080996,"y":-0.031529173254966739,"z":0.01735989935696125,"w":0.8753888607025147},"size":18.77411460876465,"orthographic":false}